RPI5_DRV8825.py
RPI5_DRV8825-1.0.0.dist-info/LICENSE
RPI5_DRV8825-1.0.0.dist-info/METADATA
RPI5_DRV8825-1.0.0.dist-info/WHEEL
RPI5_DRV8825-1.0.0.dist-info/top_level.txt
RPI5_DRV8825-1.0.0.dist-info/RECORD
