Metadata-Version: 2.2
Name: RPI5_DRV8825
Version: 1.0.0
Summary: An updated DRV8825 stepper motor driver library for Raspberry Pi 5
Author-email: Alexandru Gadin <112425293+agadin@users.noreply.github.com>
License: Unlicense
Project-URL: Homepage, https://github.com/agadin/RPI5_DRV8825
Classifier: Programming Language :: Python :: 3
Classifier: License :: Public Domain
Classifier: Operating System :: POSIX :: Linux
Requires-Python: >=3.6
License-File: LICENSE
Requires-Dist: lgpio
